pySRSLockin/__init__.py
pySRSLockin/config.json
pySRSLockin/driver.py
pySRSLockin/main.py
pySRSLockin/graphics/pause.png
pySRSLockin/graphics/play.png
pySRSLockin/graphics/refresh.png
pySRSLockin/graphics/stop.png
pySRSLockin-0.22.dist-info/METADATA
pySRSLockin-0.22.dist-info/WHEEL
pySRSLockin-0.22.dist-info/entry_points.txt
pySRSLockin-0.22.dist-info/top_level.txt
pySRSLockin-0.22.dist-info/RECORD
