Metadata-Version: 2.1
Name: pySRSLockin
Version: 0.22
Summary: A python library/GUI to access and control different models of lock-in amplifiers made by SRS.
Home-page: https://github.com/MicheleCotrufo/
Author: Michele Cotrufo
Author-email: michele.cotrufo@gmail.com
License: MIT
Platform: UNKNOWN
Requires-Dist: abstract-instrument-interface (>=0.9)
Requires-Dist: PyQt5 (>=5.15.6)
Requires-Dist: pyqtgraph
Requires-Dist: pyvisa
Requires-Dist: numpy
